temporal_boost/__init__.py
temporal_boost/boost_app.py
temporal_boost/cli/__init__.py
temporal_boost/cli/importer.py
temporal_boost/cli/process_runner.py
temporal_boost/cli/prometheus.py
temporal_boost/cli/runner.py
temporal_boost/common.py
temporal_boost/py.typed
temporal_boost/temporal/__init__.py
temporal_boost/temporal/client.py
temporal_boost/temporal/config.py
temporal_boost/temporal/runtime.py
temporal_boost/temporal/worker.py
temporal_boost/workers/__init__.py
temporal_boost/workers/asgi_registry.py
temporal_boost/workers/base.py
temporal_boost/workers/faststream_worker.py
temporal_boost/workers/granian_worker.py
temporal_boost/workers/hypercorn_worker.py
temporal_boost/workers/temporal.py
temporal_boost/workers/uvicorn_worker.py
temporal_boost-2.0.2.dist-info/METADATA
temporal_boost-2.0.2.dist-info/WHEEL
temporal_boost-2.0.2.dist-info/entry_points.txt
temporal_boost-2.0.2.dist-info/licenses/LICENSE
temporal_boost-2.0.2.dist-info/RECORD
