Metadata-Version: 2.4
Name: temporal-boost
Version: 2.0.2
Summary: Small framework for Temporal development
License: MIT
License-File: LICENSE
Keywords: temporal,framework,development,python
Author: northpowered
Author-email: you@example.com
Requires-Python: >=3.10.0,<4.0.0
Classifier: License :: OSI Approved :: MIT License
Classifier: Operating System :: OS Independent
Classifier: Programming Language :: Python :: 3
Classifier: Programming Language :: Python :: 3.10
Classifier: Programming Language :: Python :: 3.11
Classifier: Programming Language :: Python :: 3.12
Classifier: Programming Language :: Python :: 3.13
Classifier: Programming Language :: Python :: 3.14
Provides-Extra: faststream
Provides-Extra: granian
Provides-Extra: hypercorn
Provides-Extra: uvicorn
Requires-Dist: anyio ; extra == "faststream"
Requires-Dist: faststream ; extra == "faststream"
Requires-Dist: granian ; extra == "granian"
Requires-Dist: hypercorn ; extra == "hypercorn"
Requires-Dist: pydantic
Requires-Dist: pyyaml (>=6.0.0,<7.0.0)
Requires-Dist: temporalio
Requires-Dist: typer (>=0.16.0,<0.17.0)
Requires-Dist: uvicorn ; extra == "uvicorn"
Project-URL: Repository, https://github.com/northpowered/temporal-boost
